mh_logger/__init__.py
mh_logger/mh_logger.py
mh_logger/mh_rate_limit.py
mh_logger/mh_rate_limit_v2.py
mh_logger-0.1.53.dist-info/LICENSE.txt
mh_logger-0.1.53.dist-info/METADATA
mh_logger-0.1.53.dist-info/WHEEL
mh_logger-0.1.53.dist-info/top_level.txt
mh_logger-0.1.53.dist-info/RECORD
