Metadata-Version: 2.1
Name: mh-logger
Version: 0.1.53
Summary: Moonhub.ai logger to push logs into GCP Cloud Logging
Home-page: https://github.com/MoonhubTeam/logger
Author: Luis Galeana
Author-email: luis.galeana@moonhub.ai
Project-URL: Bug Tracker, https://github.com/MoonhubTeam/logger/issues
Project-URL: repository, https://github.com/MoonhubTeam/logger
Classifier: Programming Language :: Python :: 3
Classifier: License :: OSI Approved :: MIT License
Classifier: Operating System :: OS Independent
Requires-Python: >=3.6
License-File: LICENSE.txt
Requires-Dist: google-cloud-logging ==3.5.0
Requires-Dist: requests >=2.30.1
Requires-Dist: redis ==5.0.1
